[{"name":"Bulbasaur","type":"Pokémon","stage":"Basic","colours":["Grass"],"series":"mega-evolution","set":"mega-evolution","cardNumber":"001","imageSrc":"mega-evolution/mega-evolution/images/001.jpg"},{"name":"Ivysaur","type":"Pokémon","stage":"Stage 1","colours":["Grass"],"series":"mega-evolution","set":"mega-evolution","cardNumber":"002","imageSrc":"mega-evolution/mega-evolution/images/002.jpg"},{"name":"Mega Venusaur ex","type":"Pokémon","stage":"Stage 2","colours":["Grass"],"series":"mega-evolution","set":"mega-evolution","cardNumber":"003","imageSrc":"mega-evolution/mega-evolution/images/003.jpg"},{"name":"Exeggcute","type":"Pokémon","stage":"Basic","colours":["Grass"],"series":"mega-evolution","set":"mega-evolution","cardNumber":"004","imageSrc":"mega-evolution/mega-evolution/images/004.jpg"},{"name":"Exeggutor","type":"Pokémon","stage":"Stage 1","colours":["Grass"],"series":"mega-evolution","set":"mega-evolution","cardNumber":"005","imageSrc":"mega-evolution/mega-evolution/images/005.jpg"},{"name":"Tangela","type":"Pokémon","stage":"Basic","colours":["Grass"],"series":"mega-evolution","set":"mega-evolution","cardNumber":"006","imageSrc":"mega-evolution/mega-evolution/images/006.jpg"},{"name":"Tangrowth","type":"Pokémon","stage":"Stage 1","colours":["Grass"],"series":"mega-evolution","set":"mega-evolution","cardNumber":"007","imageSrc":"mega-evolution/mega-evolution/images/007.jpg"},{"name":"Chikorita","type":"Pokémon","stage":"Basic","colours":["Grass"],"series":"mega-evolution","set":"mega-evolution","cardNumber":"008","imageSrc":"mega-evolution/mega-evolution/images/008.jpg"},{"name":"Bayleef","type":"Pokémon","stage":"Stage 1","colours":["Grass"],"series":"mega-evolution","set":"mega-evolution","cardNumber":"009","imageSrc":"mega-evolution/mega-evolution/images/009.jpg"},{"name":"Meganium","type":"Pokémon","stage":"Stage 2","colours":["Grass"],"series":"mega-evolution","set":"mega-evolution","cardNumber":"010","imageSrc":"mega-evolution/mega-evolution/images/010.jpg"},{"name":"Shuckle","type":"Pokémon","stage":"Basic","colours":["Grass"],"series":"mega-evolution","set":"mega-evolution","cardNumber":"011","imageSrc":"mega-evolution/mega-evolution/images/011.jpg"},{"name":"Celebi","type":"Pokémon","stage":"Basic","colours":["Grass"],"series":"mega-evolution","set":"mega-evolution","cardNumber":"012","imageSrc":"mega-evolution/mega-evolution/images/012.jpg"},{"name":"Seedot","type":"Pokémon","stage":"Basic","colours":["Grass"],"series":"mega-evolution","set":"mega-evolution","cardNumber":"013","imageSrc":"mega-evolution/mega-evolution/images/013.jpg"},{"name":"Nuzleaf","type":"Pokémon","stage":"Stage 1","colours":["Grass"],"series":"mega-evolution","set":"mega-evolution","cardNumber":"014","imageSrc":"mega-evolution/mega-evolution/images/014.jpg"},{"name":"Shiftry","type":"Pokémon","stage":"Stage 2","colours":["Grass"],"series":"mega-evolution","set":"mega-evolution","cardNumber":"015","imageSrc":"mega-evolution/mega-evolution/images/015.jpg"},{"name":"Nincada","type":"Pokémon","stage":"Basic","colours":["Grass"],"series":"mega-evolution","set":"mega-evolution","cardNumber":"016","imageSrc":"mega-evolution/mega-evolution/images/016.jpg"},{"name":"Ninjask","type":"Pokémon","stage":"Stage 1","colours":["Grass"],"series":"mega-evolution","set":"mega-evolution","cardNumber":"017","imageSrc":"mega-evolution/mega-evolution/images/017.jpg"},{"name":"Dhelmise","type":"Pokémon","stage":"Basic","colours":["Grass"],"series":"mega-evolution","set":"mega-evolution","cardNumber":"018","imageSrc":"mega-evolution/mega-evolution/images/018.jpg"},{"name":"Vulpix","type":"Pokémon","stage":"Basic","colours":["Fire"],"series":"mega-evolution","set":"mega-evolution","cardNumber":"019","imageSrc":"mega-evolution/mega-evolution/images/019.jpg"},{"name":"Ninetales","type":"Pokémon","stage":"Stage 1","colours":["Fire"],"series":"mega-evolution","set":"mega-evolution","cardNumber":"020","imageSrc":"mega-evolution/mega-evolution/images/020.jpg"},{"name":"Numel","type":"Pokémon","stage":"Basic","colours":["Fire"],"series":"mega-evolution","set":"mega-evolution","cardNumber":"021","imageSrc":"mega-evolution/mega-evolution/images/021.jpg"},{"name":"Mega Camerupt ex","type":"Pokémon","stage":"Stage 1","colours":["Fire"],"series":"mega-evolution","set":"mega-evolution","cardNumber":"022","imageSrc":"mega-evolution/mega-evolution/images/022.jpg"},{"name":"Litleo","type":"Pokémon","stage":"Basic","colours":["Fire"],"series":"mega-evolution","set":"mega-evolution","cardNumber":"023","imageSrc":"mega-evolution/mega-evolution/images/023.jpg"},{"name":"Pyroar","type":"Pokémon","stage":"Stage 1","colours":["Fire"],"series":"mega-evolution","set":"mega-evolution","cardNumber":"024","imageSrc":"mega-evolution/mega-evolution/images/024.jpg"},{"name":"Volcanion","type":"Pokémon","stage":"Basic","colours":["Fire"],"series":"mega-evolution","set":"mega-evolution","cardNumber":"025","imageSrc":"mega-evolution/mega-evolution/images/025.jpg"},{"name":"Scorbunny","type":"Pokémon","stage":"Basic","colours":["Fire"],"series":"mega-evolution","set":"mega-evolution","cardNumber":"026","imageSrc":"mega-evolution/mega-evolution/images/026.jpg"},{"name":"Raboot","type":"Pokémon","stage":"Stage 1","colours":["Fire"],"series":"mega-evolution","set":"mega-evolution","cardNumber":"027","imageSrc":"mega-evolution/mega-evolution/images/027.jpg"},{"name":"Cinderace","type":"Pokémon","stage":"Stage 2","colours":["Fire"],"series":"mega-evolution","set":"mega-evolution","cardNumber":"028","imageSrc":"mega-evolution/mega-evolution/images/028.jpg"},{"name":"Sizzlipede","type":"Pokémon","stage":"Basic","colours":["Fire"],"series":"mega-evolution","set":"mega-evolution","cardNumber":"029","imageSrc":"mega-evolution/mega-evolution/images/029.jpg"},{"name":"Centiskorch","type":"Pokémon","stage":"Stage 1","colours":["Fire"],"series":"mega-evolution","set":"mega-evolution","cardNumber":"030","imageSrc":"mega-evolution/mega-evolution/images/030.jpg"},{"name":"Chi-Yu","type":"Pokémon","stage":"Basic","colours":["Fire"],"series":"mega-evolution","set":"mega-evolution","cardNumber":"031","imageSrc":"mega-evolution/mega-evolution/images/031.jpg"},{"name":"Mantine","type":"Pokémon","stage":"Basic","colours":["Water"],"series":"mega-evolution","set":"mega-evolution","cardNumber":"032","imageSrc":"mega-evolution/mega-evolution/images/032.jpg"},{"name":"Corphish","type":"Pokémon","stage":"Basic","colours":["Water"],"series":"mega-evolution","set":"mega-evolution","cardNumber":"033","imageSrc":"mega-evolution/mega-evolution/images/033.jpg"},{"name":"Kyogre","type":"Pokémon","stage":"Basic","colours":["Water"],"series":"mega-evolution","set":"mega-evolution","cardNumber":"034","imageSrc":"mega-evolution/mega-evolution/images/034.jpg"},{"name":"Snover","type":"Pokémon","stage":"Basic","colours":["Water"],"series":"mega-evolution","set":"mega-evolution","cardNumber":"035","imageSrc":"mega-evolution/mega-evolution/images/035.jpg"},{"name":"Mega Abomasnow ex","type":"Pokémon","stage":"Stage 1","colours":["Water"],"series":"mega-evolution","set":"mega-evolution","cardNumber":"036","imageSrc":"mega-evolution/mega-evolution/images/036.jpg"},{"name":"Clauncher","type":"Pokémon","stage":"Basic","colours":["Water"],"series":"mega-evolution","set":"mega-evolution","cardNumber":"037","imageSrc":"mega-evolution/mega-evolution/images/037.jpg"},{"name":"Clawitzer","type":"Pokémon","stage":"Stage 1","colours":["Water"],"series":"mega-evolution","set":"mega-evolution","cardNumber":"038","imageSrc":"mega-evolution/mega-evolution/images/038.jpg"},{"name":"Sobble","type":"Pokémon","stage":"Basic","colours":["Water"],"series":"mega-evolution","set":"mega-evolution","cardNumber":"039","imageSrc":"mega-evolution/mega-evolution/images/039.jpg"},{"name":"Drizzile","type":"Pokémon","stage":"Stage 1","colours":["Water"],"series":"mega-evolution","set":"mega-evolution","cardNumber":"040","imageSrc":"mega-evolution/mega-evolution/images/040.jpg"},{"name":"Inteleon","type":"Pokémon","stage":"Stage 2","colours":["Water"],"series":"mega-evolution","set":"mega-evolution","cardNumber":"041","imageSrc":"mega-evolution/mega-evolution/images/041.jpg"},{"name":"Snom","type":"Pokémon","stage":"Basic","colours":["Water"],"series":"mega-evolution","set":"mega-evolution","cardNumber":"042","imageSrc":"mega-evolution/mega-evolution/images/042.jpg"},{"name":"Frosmoth","type":"Pokémon","stage":"Stage 1","colours":["Water"],"series":"mega-evolution","set":"mega-evolution","cardNumber":"043","imageSrc":"mega-evolution/mega-evolution/images/043.jpg"},{"name":"Eiscue","type":"Pokémon","stage":"Basic","colours":["Water"],"series":"mega-evolution","set":"mega-evolution","cardNumber":"044","imageSrc":"mega-evolution/mega-evolution/images/044.jpg"},{"name":"Magnemite","type":"Pokémon","stage":"Basic","colours":["Lightning"],"series":"mega-evolution","set":"mega-evolution","cardNumber":"045","imageSrc":"mega-evolution/mega-evolution/images/045.jpg"},{"name":"Magneton","type":"Pokémon","stage":"Stage 1","colours":["Lightning"],"series":"mega-evolution","set":"mega-evolution","cardNumber":"046","imageSrc":"mega-evolution/mega-evolution/images/046.jpg"},{"name":"Magnezone","type":"Pokémon","stage":"Stage 2","colours":["Lightning"],"series":"mega-evolution","set":"mega-evolution","cardNumber":"047","imageSrc":"mega-evolution/mega-evolution/images/047.jpg"},{"name":"Raikou","type":"Pokémon","stage":"Basic","colours":["Lightning"],"series":"mega-evolution","set":"mega-evolution","cardNumber":"048","imageSrc":"mega-evolution/mega-evolution/images/048.jpg"},{"name":"Electrike","type":"Pokémon","stage":"Basic","colours":["Lightning"],"series":"mega-evolution","set":"mega-evolution","cardNumber":"049","imageSrc":"mega-evolution/mega-evolution/images/049.jpg"},{"name":"Mega Manectric ex","type":"Pokémon","stage":"Stage 1","colours":["Lightning"],"series":"mega-evolution","set":"mega-evolution","cardNumber":"050","imageSrc":"mega-evolution/mega-evolution/images/050.jpg"},{"name":"Pachirisu","type":"Pokémon","stage":"Basic","colours":["Lightning"],"series":"mega-evolution","set":"mega-evolution","cardNumber":"051","imageSrc":"mega-evolution/mega-evolution/images/051.jpg"},{"name":"Helioptile","type":"Pokémon","stage":"Basic","colours":["Lightning"],"series":"mega-evolution","set":"mega-evolution","cardNumber":"052","imageSrc":"mega-evolution/mega-evolution/images/052.jpg"},{"name":"Heliolisk","type":"Pokémon","stage":"Stage 1","colours":["Lightning"],"series":"mega-evolution","set":"mega-evolution","cardNumber":"053","imageSrc":"mega-evolution/mega-evolution/images/053.jpg"},{"name":"Abra","type":"Pokémon","stage":"Basic","colours":["Psychic"],"series":"mega-evolution","set":"mega-evolution","cardNumber":"054","imageSrc":"mega-evolution/mega-evolution/images/054.jpg"},{"name":"Kadabra","type":"Pokémon","stage":"Stage 1","colours":["Psychic"],"series":"mega-evolution","set":"mega-evolution","cardNumber":"055","imageSrc":"mega-evolution/mega-evolution/images/055.jpg"},{"name":"Alakazam","type":"Pokémon","stage":"Stage 2","colours":["Psychic"],"series":"mega-evolution","set":"mega-evolution","cardNumber":"056","imageSrc":"mega-evolution/mega-evolution/images/056.jpg"},{"name":"Jynx","type":"Pokémon","stage":"Basic","colours":["Psychic"],"series":"mega-evolution","set":"mega-evolution","cardNumber":"057","imageSrc":"mega-evolution/mega-evolution/images/057.jpg"},{"name":"Ralts","type":"Pokémon","stage":"Basic","colours":["Psychic"],"series":"mega-evolution","set":"mega-evolution","cardNumber":"058","imageSrc":"mega-evolution/mega-evolution/images/058.jpg"},{"name":"Kirlia","type":"Pokémon","stage":"Stage 1","colours":["Psychic"],"series":"mega-evolution","set":"mega-evolution","cardNumber":"059","imageSrc":"mega-evolution/mega-evolution/images/059.jpg"},{"name":"Mega Gardevoir ex","type":"Pokémon","stage":"Stage 2","colours":["Psychic"],"series":"mega-evolution","set":"mega-evolution","cardNumber":"060","imageSrc":"mega-evolution/mega-evolution/images/060.jpg"},{"name":"Shedinja","type":"Pokémon","stage":"Stage 1","colours":["Psychic"],"series":"mega-evolution","set":"mega-evolution","cardNumber":"061","imageSrc":"mega-evolution/mega-evolution/images/061.jpg"},{"name":"Spoink","type":"Pokémon","stage":"Basic","colours":["Psychic"],"series":"mega-evolution","set":"mega-evolution","cardNumber":"062","imageSrc":"mega-evolution/mega-evolution/images/062.jpg"},{"name":"Grumpig","type":"Pokémon","stage":"Stage 1","colours":["Psychic"],"series":"mega-evolution","set":"mega-evolution","cardNumber":"063","imageSrc":"mega-evolution/mega-evolution/images/063.jpg"},{"name":"Xerneas","type":"Pokémon","stage":"Basic","colours":["Psychic"],"series":"mega-evolution","set":"mega-evolution","cardNumber":"064","imageSrc":"mega-evolution/mega-evolution/images/064.jpg"},{"name":"Greavard","type":"Pokémon","stage":"Basic","colours":["Psychic"],"series":"mega-evolution","set":"mega-evolution","cardNumber":"065","imageSrc":"mega-evolution/mega-evolution/images/065.jpg"},{"name":"Houndstone","type":"Pokémon","stage":"Stage 1","colours":["Psychic"],"series":"mega-evolution","set":"mega-evolution","cardNumber":"066","imageSrc":"mega-evolution/mega-evolution/images/066.jpg"},{"name":"Gimmighoul","type":"Pokémon","stage":"Basic","colours":["Psychic"],"series":"mega-evolution","set":"mega-evolution","cardNumber":"067","imageSrc":"mega-evolution/mega-evolution/images/067.jpg"},{"name":"Sandshrew","type":"Pokémon","stage":"Basic","colours":["Fighting"],"series":"mega-evolution","set":"mega-evolution","cardNumber":"068","imageSrc":"mega-evolution/mega-evolution/images/068.jpg"},{"name":"Sandslash","type":"Pokémon","stage":"Stage 1","colours":["Fighting"],"series":"mega-evolution","set":"mega-evolution","cardNumber":"069","imageSrc":"mega-evolution/mega-evolution/images/069.jpg"},{"name":"Onix","type":"Pokémon","stage":"Basic","colours":["Fighting"],"series":"mega-evolution","set":"mega-evolution","cardNumber":"070","imageSrc":"mega-evolution/mega-evolution/images/070.jpg"},{"name":"Tyrogue","type":"Pokémon","stage":"Basic","colours":["Fighting"],"series":"mega-evolution","set":"mega-evolution","cardNumber":"071","imageSrc":"mega-evolution/mega-evolution/images/071.jpg"},{"name":"Makuhita","type":"Pokémon","stage":"Basic","colours":["Fighting"],"series":"mega-evolution","set":"mega-evolution","cardNumber":"072","imageSrc":"mega-evolution/mega-evolution/images/072.jpg"},{"name":"Hariyama","type":"Pokémon","stage":"Stage 1","colours":["Fighting"],"series":"mega-evolution","set":"mega-evolution","cardNumber":"073","imageSrc":"mega-evolution/mega-evolution/images/073.jpg"},{"name":"Lunatone","type":"Pokémon","stage":"Basic","colours":["Fighting"],"series":"mega-evolution","set":"mega-evolution","cardNumber":"074","imageSrc":"mega-evolution/mega-evolution/images/074.jpg"},{"name":"Solrock","type":"Pokémon","stage":"Basic","colours":["Fighting"],"series":"mega-evolution","set":"mega-evolution","cardNumber":"075","imageSrc":"mega-evolution/mega-evolution/images/075.jpg"},{"name":"Riolu","type":"Pokémon","stage":"Basic","colours":["Fighting"],"series":"mega-evolution","set":"mega-evolution","cardNumber":"076","imageSrc":"mega-evolution/mega-evolution/images/076.jpg"},{"name":"Mega Lucario ex","type":"Pokémon","stage":"Stage 1","colours":["Fighting"],"series":"mega-evolution","set":"mega-evolution","cardNumber":"077","imageSrc":"mega-evolution/mega-evolution/images/077.jpg"},{"name":"Croagunk","type":"Pokémon","stage":"Basic","colours":["Fighting"],"series":"mega-evolution","set":"mega-evolution","cardNumber":"078","imageSrc":"mega-evolution/mega-evolution/images/078.jpg"},{"name":"Toxicroak","type":"Pokémon","stage":"Stage 1","colours":["Fighting"],"series":"mega-evolution","set":"mega-evolution","cardNumber":"079","imageSrc":"mega-evolution/mega-evolution/images/079.jpg"},{"name":"Marshadow","type":"Pokémon","stage":"Basic","colours":["Fighting"],"series":"mega-evolution","set":"mega-evolution","cardNumber":"080","imageSrc":"mega-evolution/mega-evolution/images/080.jpg"},{"name":"Stonjourner","type":"Pokémon","stage":"Basic","colours":["Fighting"],"series":"mega-evolution","set":"mega-evolution","cardNumber":"081","imageSrc":"mega-evolution/mega-evolution/images/081.jpg"},{"name":"Nacli","type":"Pokémon","stage":"Basic","colours":["Fighting"],"series":"mega-evolution","set":"mega-evolution","cardNumber":"082","imageSrc":"mega-evolution/mega-evolution/images/082.jpg"},{"name":"Naclstack","type":"Pokémon","stage":"Stage 1","colours":["Fighting"],"series":"mega-evolution","set":"mega-evolution","cardNumber":"083","imageSrc":"mega-evolution/mega-evolution/images/083.jpg"},{"name":"Garganacl","type":"Pokémon","stage":"Stage 2","colours":["Fighting"],"series":"mega-evolution","set":"mega-evolution","cardNumber":"084","imageSrc":"mega-evolution/mega-evolution/images/084.jpg"},{"name":"Crawdaunt","type":"Pokémon","stage":"Stage 1","colours":["Darkness"],"series":"mega-evolution","set":"mega-evolution","cardNumber":"085","imageSrc":"mega-evolution/mega-evolution/images/085.jpg"},{"name":"Mega Absol ex","type":"Pokémon","stage":"Basic","colours":["Darkness"],"series":"mega-evolution","set":"mega-evolution","cardNumber":"086","imageSrc":"mega-evolution/mega-evolution/images/086.jpg"},{"name":"Spiritomb","type":"Pokémon","stage":"Basic","colours":["Darkness"],"series":"mega-evolution","set":"mega-evolution","cardNumber":"087","imageSrc":"mega-evolution/mega-evolution/images/087.jpg"},{"name":"Yveltal","type":"Pokémon","stage":"Basic","colours":["Darkness"],"series":"mega-evolution","set":"mega-evolution","cardNumber":"088","imageSrc":"mega-evolution/mega-evolution/images/088.jpg"},{"name":"Nickit","type":"Pokémon","stage":"Basic","colours":["Darkness"],"series":"mega-evolution","set":"mega-evolution","cardNumber":"089","imageSrc":"mega-evolution/mega-evolution/images/089.jpg"},{"name":"Thievul","type":"Pokémon","stage":"Stage 1","colours":["Darkness"],"series":"mega-evolution","set":"mega-evolution","cardNumber":"090","imageSrc":"mega-evolution/mega-evolution/images/090.jpg"},{"name":"Shroodle","type":"Pokémon","stage":"Basic","colours":["Darkness"],"series":"mega-evolution","set":"mega-evolution","cardNumber":"091","imageSrc":"mega-evolution/mega-evolution/images/091.jpg"},{"name":"Grafaiai","type":"Pokémon","stage":"Stage 1","colours":["Darkness"],"series":"mega-evolution","set":"mega-evolution","cardNumber":"092","imageSrc":"mega-evolution/mega-evolution/images/092.jpg"},{"name":"Steelix","type":"Pokémon","stage":"Stage 1","colours":["Metal"],"series":"mega-evolution","set":"mega-evolution","cardNumber":"093","imageSrc":"mega-evolution/mega-evolution/images/093.jpg"},{"name":"Mega Mawile ex","type":"Pokémon","stage":"Basic","colours":["Metal"],"series":"mega-evolution","set":"mega-evolution","cardNumber":"094","imageSrc":"mega-evolution/mega-evolution/images/094.jpg"},{"name":"Dialga","type":"Pokémon","stage":"Basic","colours":["Metal"],"series":"mega-evolution","set":"mega-evolution","cardNumber":"095","imageSrc":"mega-evolution/mega-evolution/images/095.jpg"},{"name":"Tinkatink","type":"Pokémon","stage":"Basic","colours":["Metal"],"series":"mega-evolution","set":"mega-evolution","cardNumber":"096","imageSrc":"mega-evolution/mega-evolution/images/096.jpg"},{"name":"Tinkatuff","type":"Pokémon","stage":"Stage 1","colours":["Metal"],"series":"mega-evolution","set":"mega-evolution","cardNumber":"097","imageSrc":"mega-evolution/mega-evolution/images/097.jpg"},{"name":"Tinkaton","type":"Pokémon","stage":"Stage 2","colours":["Metal"],"series":"mega-evolution","set":"mega-evolution","cardNumber":"098","imageSrc":"mega-evolution/mega-evolution/images/098.jpg"},{"name":"Gholdengo","type":"Pokémon","stage":"Stage 1","colours":["Metal"],"series":"mega-evolution","set":"mega-evolution","cardNumber":"099","imageSrc":"mega-evolution/mega-evolution/images/099.jpg"},{"name":"Mega Latias ex","type":"Pokémon","stage":"Basic","colours":["Dragon"],"series":"mega-evolution","set":"mega-evolution","cardNumber":"100","imageSrc":"mega-evolution/mega-evolution/images/100.jpg"},{"name":"Latios","type":"Pokémon","stage":"Basic","colours":["Dragon"],"series":"mega-evolution","set":"mega-evolution","cardNumber":"101","imageSrc":"mega-evolution/mega-evolution/images/101.jpg"},{"name":"Spearow","type":"Pokémon","stage":"Basic","colours":["Colorless"],"series":"mega-evolution","set":"mega-evolution","cardNumber":"102","imageSrc":"mega-evolution/mega-evolution/images/102.jpg"},{"name":"Fearow","type":"Pokémon","stage":"Stage 1","colours":["Colorless"],"series":"mega-evolution","set":"mega-evolution","cardNumber":"103","imageSrc":"mega-evolution/mega-evolution/images/103.jpg"},{"name":"Mega Kangaskhan ex","type":"Pokémon","stage":"Basic","colours":["Colorless"],"series":"mega-evolution","set":"mega-evolution","cardNumber":"104","imageSrc":"mega-evolution/mega-evolution/images/104.jpg"},{"name":"Delibird","type":"Pokémon","stage":"Basic","colours":["Colorless"],"series":"mega-evolution","set":"mega-evolution","cardNumber":"105","imageSrc":"mega-evolution/mega-evolution/images/105.jpg"},{"name":"Miltank","type":"Pokémon","stage":"Basic","colours":["Colorless"],"series":"mega-evolution","set":"mega-evolution","cardNumber":"106","imageSrc":"mega-evolution/mega-evolution/images/106.jpg"},{"name":"Buneary","type":"Pokémon","stage":"Basic","colours":["Colorless"],"series":"mega-evolution","set":"mega-evolution","cardNumber":"107","imageSrc":"mega-evolution/mega-evolution/images/107.jpg"},{"name":"Lopunny","type":"Pokémon","stage":"Stage 1","colours":["Colorless"],"series":"mega-evolution","set":"mega-evolution","cardNumber":"108","imageSrc":"mega-evolution/mega-evolution/images/108.jpg"},{"name":"Yungoos","type":"Pokémon","stage":"Basic","colours":["Colorless"],"series":"mega-evolution","set":"mega-evolution","cardNumber":"109","imageSrc":"mega-evolution/mega-evolution/images/109.jpg"},{"name":"Gumshoos","type":"Pokémon","stage":"Stage 1","colours":["Colorless"],"series":"mega-evolution","set":"mega-evolution","cardNumber":"110","imageSrc":"mega-evolution/mega-evolution/images/110.jpg"},{"name":"Stufful","type":"Pokémon","stage":"Basic","colours":["Colorless"],"series":"mega-evolution","set":"mega-evolution","cardNumber":"111","imageSrc":"mega-evolution/mega-evolution/images/111.jpg"},{"name":"Bewear","type":"Pokémon","stage":"Stage 1","colours":["Colorless"],"series":"mega-evolution","set":"mega-evolution","cardNumber":"112","imageSrc":"mega-evolution/mega-evolution/images/112.jpg"},{"name":"Acerola’s Mischief","type":"Trainer","series":"mega-evolution","set":"mega-evolution","cardNumber":"113","imageSrc":"mega-evolution/mega-evolution/images/113.jpg"},{"name":"Boss’s Orders","type":"Trainer","series":"mega-evolution","set":"mega-evolution","cardNumber":"114","imageSrc":"mega-evolution/mega-evolution/images/114.jpg"},{"name":"Energy Switch","type":"Trainer","series":"mega-evolution","set":"mega-evolution","cardNumber":"115","imageSrc":"mega-evolution/mega-evolution/images/115.jpg"},{"name":"Fighting Gong","type":"Trainer","series":"mega-evolution","set":"mega-evolution","cardNumber":"116","imageSrc":"mega-evolution/mega-evolution/images/116.jpg"},{"name":"Forest of Vitality","type":"Trainer","series":"mega-evolution","set":"mega-evolution","cardNumber":"117","imageSrc":"mega-evolution/mega-evolution/images/117.jpg"},{"name":"Iron Defender","type":"Trainer","series":"mega-evolution","set":"mega-evolution","cardNumber":"118","imageSrc":"mega-evolution/mega-evolution/images/118.jpg"},{"name":"Lillie’s Determination","type":"Trainer","series":"mega-evolution","set":"mega-evolution","cardNumber":"119","imageSrc":"mega-evolution/mega-evolution/images/119.jpg"},{"name":"Lt. Surge’s Bargain","type":"Trainer","series":"mega-evolution","set":"mega-evolution","cardNumber":"120","imageSrc":"mega-evolution/mega-evolution/images/120.jpg"},{"name":"Mega Signal","type":"Trainer","series":"mega-evolution","set":"mega-evolution","cardNumber":"121","imageSrc":"mega-evolution/mega-evolution/images/121.jpg"},{"name":"Mystery Garden","type":"Trainer","series":"mega-evolution","set":"mega-evolution","cardNumber":"122","imageSrc":"mega-evolution/mega-evolution/images/122.jpg"},{"name":"Pokémon Center Lady","type":"Trainer","series":"mega-evolution","set":"mega-evolution","cardNumber":"123","imageSrc":"mega-evolution/mega-evolution/images/123.jpg"},{"name":"Premium Power Pro","type":"Trainer","series":"mega-evolution","set":"mega-evolution","cardNumber":"124","imageSrc":"mega-evolution/mega-evolution/images/124.jpg"},{"name":"Rare Candy","type":"Trainer","series":"mega-evolution","set":"mega-evolution","cardNumber":"125","imageSrc":"mega-evolution/mega-evolution/images/125.jpg"},{"name":"Repel","type":"Trainer","series":"mega-evolution","set":"mega-evolution","cardNumber":"126","imageSrc":"mega-evolution/mega-evolution/images/126.jpg"},{"name":"Risky Ruins","type":"Trainer","series":"mega-evolution","set":"mega-evolution","cardNumber":"127","imageSrc":"mega-evolution/mega-evolution/images/127.jpg"},{"name":"Strange Timepiece","type":"Trainer","series":"mega-evolution","set":"mega-evolution","cardNumber":"128","imageSrc":"mega-evolution/mega-evolution/images/128.jpg"},{"name":"Surfing Beach","type":"Trainer","series":"mega-evolution","set":"mega-evolution","cardNumber":"129","imageSrc":"mega-evolution/mega-evolution/images/129.jpg"},{"name":"Switch","type":"Trainer","series":"mega-evolution","set":"mega-evolution","cardNumber":"130","imageSrc":"mega-evolution/mega-evolution/images/130.jpg"},{"name":"Ultra Ball","type":"Trainer","series":"mega-evolution","set":"mega-evolution","cardNumber":"131","imageSrc":"mega-evolution/mega-evolution/images/131.jpg"},{"name":"Wally’s Compassion","type":"Trainer","series":"mega-evolution","set":"mega-evolution","cardNumber":"132","imageSrc":"mega-evolution/mega-evolution/images/132.jpg"},{"name":"Bulbasaur","type":"Pokémon","stage":"Basic","colours":["Grass"],"series":"mega-evolution","set":"mega-evolution","cardNumber":"133","imageSrc":"mega-evolution/mega-evolution/images/133.jpg"},{"name":"Ivysaur","type":"Pokémon","stage":"Stage 1","colours":["Grass"],"series":"mega-evolution","set":"mega-evolution","cardNumber":"134","imageSrc":"mega-evolution/mega-evolution/images/134.jpg"},{"name":"Exeggutor","type":"Pokémon","stage":"Stage 1","colours":["Grass"],"series":"mega-evolution","set":"mega-evolution","cardNumber":"135","imageSrc":"mega-evolution/mega-evolution/images/135.jpg"},{"name":"Shuckle","type":"Pokémon","stage":"Basic","colours":["Grass"],"series":"mega-evolution","set":"mega-evolution","cardNumber":"136","imageSrc":"mega-evolution/mega-evolution/images/136.jpg"},{"name":"Ninjask","type":"Pokémon","stage":"Stage 1","colours":["Grass"],"series":"mega-evolution","set":"mega-evolution","cardNumber":"137","imageSrc":"mega-evolution/mega-evolution/images/137.jpg"},{"name":"Vulpix","type":"Pokémon","stage":"Basic","colours":["Fire"],"series":"mega-evolution","set":"mega-evolution","cardNumber":"138","imageSrc":"mega-evolution/mega-evolution/images/138.jpg"},{"name":"Litleo","type":"Pokémon","stage":"Basic","colours":["Fire"],"series":"mega-evolution","set":"mega-evolution","cardNumber":"139","imageSrc":"mega-evolution/mega-evolution/images/139.jpg"},{"name":"Snover","type":"Pokémon","stage":"Basic","colours":["Water"],"series":"mega-evolution","set":"mega-evolution","cardNumber":"140","imageSrc":"mega-evolution/mega-evolution/images/140.jpg"},{"name":"Clawitzer","type":"Pokémon","stage":"Stage 1","colours":["Water"],"series":"mega-evolution","set":"mega-evolution","cardNumber":"141","imageSrc":"mega-evolution/mega-evolution/images/141.jpg"},{"name":"Inteleon","type":"Pokémon","stage":"Stage 2","colours":["Water"],"series":"mega-evolution","set":"mega-evolution","cardNumber":"142","imageSrc":"mega-evolution/mega-evolution/images/142.jpg"},{"name":"Helioptile","type":"Pokémon","stage":"Basic","colours":["Lightning"],"series":"mega-evolution","set":"mega-evolution","cardNumber":"143","imageSrc":"mega-evolution/mega-evolution/images/143.jpg"},{"name":"Shedinja","type":"Pokémon","stage":"Stage 1","colours":["Psychic"],"series":"mega-evolution","set":"mega-evolution","cardNumber":"144","imageSrc":"mega-evolution/mega-evolution/images/144.jpg"},{"name":"Houndstone","type":"Pokémon","stage":"Stage 1","colours":["Psychic"],"series":"mega-evolution","set":"mega-evolution","cardNumber":"145","imageSrc":"mega-evolution/mega-evolution/images/145.jpg"},{"name":"Marshadow","type":"Pokémon","stage":"Basic","colours":["Fighting"],"series":"mega-evolution","set":"mega-evolution","cardNumber":"146","imageSrc":"mega-evolution/mega-evolution/images/146.jpg"},{"name":"Garganacl","type":"Pokémon","stage":"Stage 2","colours":["Fighting"],"series":"mega-evolution","set":"mega-evolution","cardNumber":"147","imageSrc":"mega-evolution/mega-evolution/images/147.jpg"},{"name":"Spiritomb","type":"Pokémon","stage":"Basic","colours":["Darkness"],"series":"mega-evolution","set":"mega-evolution","cardNumber":"148","imageSrc":"mega-evolution/mega-evolution/images/148.jpg"},{"name":"Shroodle","type":"Pokémon","stage":"Basic","colours":["Darkness"],"series":"mega-evolution","set":"mega-evolution","cardNumber":"149","imageSrc":"mega-evolution/mega-evolution/images/149.jpg"},{"name":"Steelix","type":"Pokémon","stage":"Stage 1","colours":["Metal"],"series":"mega-evolution","set":"mega-evolution","cardNumber":"150","imageSrc":"mega-evolution/mega-evolution/images/150.jpg"},{"name":"Spearow","type":"Pokémon","stage":"Basic","colours":["Colorless"],"series":"mega-evolution","set":"mega-evolution","cardNumber":"151","imageSrc":"mega-evolution/mega-evolution/images/151.jpg"},{"name":"Delibird","type":"Pokémon","stage":"Basic","colours":["Colorless"],"series":"mega-evolution","set":"mega-evolution","cardNumber":"152","imageSrc":"mega-evolution/mega-evolution/images/152.jpg"},{"name":"Gumshoos","type":"Pokémon","stage":"Stage 1","colours":["Colorless"],"series":"mega-evolution","set":"mega-evolution","cardNumber":"153","imageSrc":"mega-evolution/mega-evolution/images/153.jpg"},{"name":"Stufful","type":"Pokémon","stage":"Basic","colours":["Colorless"],"series":"mega-evolution","set":"mega-evolution","cardNumber":"154","imageSrc":"mega-evolution/mega-evolution/images/154.jpg"},{"name":"Mega Venusaur ex","type":"Pokémon","stage":"Stage 2","colours":["Grass"],"series":"mega-evolution","set":"mega-evolution","cardNumber":"155","imageSrc":"mega-evolution/mega-evolution/images/155.jpg"},{"name":"Mega Camerupt ex","type":"Pokémon","stage":"Stage 1","colours":["Fire"],"series":"mega-evolution","set":"mega-evolution","cardNumber":"156","imageSrc":"mega-evolution/mega-evolution/images/156.jpg"},{"name":"Mega Abomasnow ex","type":"Pokémon","stage":"Stage 1","colours":["Water"],"series":"mega-evolution","set":"mega-evolution","cardNumber":"157","imageSrc":"mega-evolution/mega-evolution/images/157.jpg"},{"name":"Mega Manectric ex","type":"Pokémon","stage":"Stage 1","colours":["Lightning"],"series":"mega-evolution","set":"mega-evolution","cardNumber":"158","imageSrc":"mega-evolution/mega-evolution/images/158.jpg"},{"name":"Mega Gardevoir ex","type":"Pokémon","stage":"Stage 2","colours":["Psychic"],"series":"mega-evolution","set":"mega-evolution","cardNumber":"159","imageSrc":"mega-evolution/mega-evolution/images/159.jpg"},{"name":"Mega Lucario ex","type":"Pokémon","stage":"Stage 1","colours":["Fighting"],"series":"mega-evolution","set":"mega-evolution","cardNumber":"160","imageSrc":"mega-evolution/mega-evolution/images/160.jpg"},{"name":"Mega Absol ex","type":"Pokémon","stage":"Basic","colours":["Darkness"],"series":"mega-evolution","set":"mega-evolution","cardNumber":"161","imageSrc":"mega-evolution/mega-evolution/images/161.jpg"},{"name":"Mega Mawile ex","type":"Pokémon","stage":"Basic","colours":["Metal"],"series":"mega-evolution","set":"mega-evolution","cardNumber":"162","imageSrc":"mega-evolution/mega-evolution/images/162.jpg"},{"name":"Mega Latias ex","type":"Pokémon","stage":"Basic","colours":["Dragon"],"series":"mega-evolution","set":"mega-evolution","cardNumber":"163","imageSrc":"mega-evolution/mega-evolution/images/163.jpg"},{"name":"Mega Kangaskhan ex","type":"Pokémon","stage":"Basic","colours":["Colorless"],"series":"mega-evolution","set":"mega-evolution","cardNumber":"164","imageSrc":"mega-evolution/mega-evolution/images/164.jpg"},{"name":"Acerola’s Mischief","type":"Trainer","series":"mega-evolution","set":"mega-evolution","cardNumber":"165","imageSrc":"mega-evolution/mega-evolution/images/165.jpg"},{"name":"Air Balloon","type":"Trainer","series":"mega-evolution","set":"mega-evolution","cardNumber":"166","imageSrc":"mega-evolution/mega-evolution/images/166.jpg"},{"name":"Buddy-Buddy Poffin","type":"Trainer","series":"mega-evolution","set":"mega-evolution","cardNumber":"167","imageSrc":"mega-evolution/mega-evolution/images/167.jpg"},{"name":"Fighting Gong","type":"Trainer","series":"mega-evolution","set":"mega-evolution","cardNumber":"168","imageSrc":"mega-evolution/mega-evolution/images/168.jpg"},{"name":"Lillie’s Determination","type":"Trainer","series":"mega-evolution","set":"mega-evolution","cardNumber":"169","imageSrc":"mega-evolution/mega-evolution/images/169.jpg"},{"name":"Lt. Surge’s Bargain","type":"Trainer","series":"mega-evolution","set":"mega-evolution","cardNumber":"170","imageSrc":"mega-evolution/mega-evolution/images/170.jpg"},{"name":"Mega Signal","type":"Trainer","series":"mega-evolution","set":"mega-evolution","cardNumber":"171","imageSrc":"mega-evolution/mega-evolution/images/171.jpg"},{"name":"Mystery Garden","type":"Trainer","series":"mega-evolution","set":"mega-evolution","cardNumber":"172","imageSrc":"mega-evolution/mega-evolution/images/172.jpg"},{"name":"Night Stretcher","type":"Trainer","series":"mega-evolution","set":"mega-evolution","cardNumber":"173","imageSrc":"mega-evolution/mega-evolution/images/173.jpg"},{"name":"Premium Power Pro","type":"Trainer","series":"mega-evolution","set":"mega-evolution","cardNumber":"174","imageSrc":"mega-evolution/mega-evolution/images/174.jpg"},{"name":"Rare Candy","type":"Trainer","series":"mega-evolution","set":"mega-evolution","cardNumber":"175","imageSrc":"mega-evolution/mega-evolution/images/175.jpg"},{"name":"Wally’s Compassion","type":"Trainer","series":"mega-evolution","set":"mega-evolution","cardNumber":"176","imageSrc":"mega-evolution/mega-evolution/images/176.jpg"},{"name":"Mega Venusaur ex","type":"Pokémon","stage":"Stage 2","colours":["Grass"],"series":"mega-evolution","set":"mega-evolution","cardNumber":"177","imageSrc":"mega-evolution/mega-evolution/images/177.jpg"},{"name":"Mega Gardevoir ex","type":"Pokémon","stage":"Stage 2","colours":["Psychic"],"series":"mega-evolution","set":"mega-evolution","cardNumber":"178","imageSrc":"mega-evolution/mega-evolution/images/178.jpg"},{"name":"Mega Lucario ex","type":"Pokémon","stage":"Stage 1","colours":["Fighting"],"series":"mega-evolution","set":"mega-evolution","cardNumber":"179","imageSrc":"mega-evolution/mega-evolution/images/179.jpg"},{"name":"Mega Absol ex","type":"Pokémon","stage":"Basic","colours":["Darkness"],"series":"mega-evolution","set":"mega-evolution","cardNumber":"180","imageSrc":"mega-evolution/mega-evolution/images/180.jpg"},{"name":"Mega Latias ex","type":"Pokémon","stage":"Basic","colours":["Dragon"],"series":"mega-evolution","set":"mega-evolution","cardNumber":"181","imageSrc":"mega-evolution/mega-evolution/images/181.jpg"},{"name":"Mega Kangaskhan ex","type":"Pokémon","stage":"Basic","colours":["Colorless"],"series":"mega-evolution","set":"mega-evolution","cardNumber":"182","imageSrc":"mega-evolution/mega-evolution/images/182.jpg"},{"name":"Acerola’s Mischief","type":"Trainer","series":"mega-evolution","set":"mega-evolution","cardNumber":"183","imageSrc":"mega-evolution/mega-evolution/images/183.jpg"},{"name":"Lillie’s Determination","type":"Trainer","series":"mega-evolution","set":"mega-evolution","cardNumber":"184","imageSrc":"mega-evolution/mega-evolution/images/184.jpg"},{"name":"Lt. Surge’s Bargain","type":"Trainer","series":"mega-evolution","set":"mega-evolution","cardNumber":"185","imageSrc":"mega-evolution/mega-evolution/images/185.jpg"},{"name":"Wally’s Compassion","type":"Trainer","series":"mega-evolution","set":"mega-evolution","cardNumber":"186","imageSrc":"mega-evolution/mega-evolution/images/186.jpg"},{"name":"Mega Gardevoir ex","type":"Pokémon","stage":"Stage 2","colours":["Psychic"],"series":"mega-evolution","set":"mega-evolution","cardNumber":"187","imageSrc":"mega-evolution/mega-evolution/images/187.jpg"},{"name":"Mega Lucario ex","type":"Pokémon","stage":"Stage 1","colours":["Fighting"],"series":"mega-evolution","set":"mega-evolution","cardNumber":"188","imageSrc":"mega-evolution/mega-evolution/images/188.jpg"}]